shadowpasser/__init__.py
shadowpasser/__main__.py
shadowpasser/app.py
shadowpasser-1.1.1.dist-info/METADATA
shadowpasser-1.1.1.dist-info/WHEEL
shadowpasser-1.1.1.dist-info/entry_points.txt
shadowpasser-1.1.1.dist-info/top_level.txt
shadowpasser-1.1.1.dist-info/RECORD
