Metadata-Version: 2.4
Name: shadowpasser
Version: 1.1.1
Summary: IAMNEO Restriction Bypasser for RMKEC Students
Author: Team ShadowCryptics
Classifier: Programming Language :: Python :: 3
Classifier: License :: OSI Approved :: MIT License
Classifier: Operating System :: OS Independent
Requires-Python: >=3.6
Requires-Dist: PyQt5
Requires-Dist: PyQtWebEngine
Dynamic: author
Dynamic: classifier
Dynamic: requires-dist
Dynamic: requires-python
Dynamic: summary
